<?xml version="1.0" encoding="utf-8" ?>
<dwsync>
<file name="Andres.htm" server="ftp.corimaencolombia.com//www/" local="128781648865468750" remote="128781654000000000" />
<file name="Antioquia.htm" server="ftp.corimaencolombia.com//www/" local="128781648865468750" remote="128781654000000000" />
<file name="Caldas.htm" server="ftp.corimaencolombia.com//www/" local="128781648866093750" remote="128781654000000000" />
<file name="Casanare.htm" server="ftp.corimaencolombia.com//www/" local="128781648866250000" remote="128781654000000000" />
<file name="Cauca.htm" server="ftp.corimaencolombia.com//www/" local="128781648866406250" remote="128781654000000000" />
<file name="Cesar.htm" server="ftp.corimaencolombia.com//www/" local="128781648866406250" remote="128781654000000000" />
<file name="Choco.htm" server="ftp.corimaencolombia.com//www/" local="128781648866562500" remote="128781654000000000" />
<file name="Cordoba.htm" server="ftp.corimaencolombia.com//www/" local="128781648866718750" remote="128781654600000000" />
<file name="Cundinamarca.htm" server="ftp.corimaencolombia.com//www/" local="128781648866718750" remote="128781654600000000" />
<file name="Guajira.htm" server="ftp.corimaencolombia.com//www/" local="128781648867187500" remote="128781654600000000" />
<file name="Guaviare.htm" server="ftp.corimaencolombia.com//www/" local="128781648867343750" remote="128781654600000000" />
<file name="Huila.htm" server="ftp.corimaencolombia.com//www/" local="128781648867500000" remote="128781654600000000" />
<file name="Magdalena.htm" server="ftp.corimaencolombia.com//www/" local="128781648867500000" remote="128781654600000000" />
<file name="Meta.htm" server="ftp.corimaencolombia.com//www/" local="128781648867656250" remote="128781654600000000" />
<file name="NSantander.htm" server="ftp.corimaencolombia.com//www/" local="128781648867968750" remote="128781654600000000" />
<file name="Narinno.htm" server="ftp.corimaencolombia.com//www/" local="128781648867812500" remote="128781654600000000" />
<file name="Putumayo.htm" server="ftp.corimaencolombia.com//www/" local="128781648867968750" remote="128781654600000000" />
<file name="Quindio.htm" server="ftp.corimaencolombia.com//www/" local="128781648868125000" remote="128781654600000000" />
<file name="Risaralda.htm" server="ftp.corimaencolombia.com//www/" local="128781648868125000" remote="128781654600000000" />
<file name="Santander.htm" server="ftp.corimaencolombia.com//www/" local="128781648868281250" remote="128781654600000000" />
<file name="Sucre.htm" server="ftp.corimaencolombia.com//www/" local="128781648868437500" remote="128781654600000000" />
<file name="Tolima.htm" server="ftp.corimaencolombia.com//www/" local="128781648868437500" remote="128781655200000000" />
<file name="Valle.htm" server="ftp.corimaencolombia.com//www/" local="128781648868593750" remote="128781655200000000" />
<file name="Vaupes.htm" server="ftp.corimaencolombia.com//www/" local="128781648868750000" remote="128781655200000000" />
<file name="Vichada.htm" server="ftp.corimaencolombia.com//www/" local="128781648868750000" remote="128781655200000000" />
<file name="amazonas.htm" server="ftp.corimaencolombia.com//www/" local="128781648865312500" remote="128781654000000000" />
<file name="arauca.htm" server="ftp.corimaencolombia.com//www/" local="128781648865625000" remote="128781654000000000" />
<file name="atla.htm" server="ftp.corimaencolombia.com//www/" local="128781648865781250" remote="128781654000000000" />
<file name="boli.htm" server="ftp.corimaencolombia.com//www/" local="128781648865781250" remote="128781654000000000" />
<file name="boya.htm" server="ftp.corimaencolombia.com//www/" local="128781648865937500" remote="128781654000000000" />
<file name="caqueta.htm" server="ftp.corimaencolombia.com//www/" local="128781648866093750" remote="128781654000000000" />
<file name="conquest.mid" server="ftp.corimaencolombia.com//www/" local="128760168000000000" remote="128781654600000000" />
<file name="fcol.htm" server="ftp.corimaencolombia.com//www/" local="128781648866875000" remote="128781654600000000" />
<file name="fcolombia.htm" server="ftp.corimaencolombia.com//www/" local="128781648867031250" remote="128781654600000000" />
<file name="guainia.htm" server="ftp.corimaencolombia.com//www/" local="128781648867187500" remote="128781654600000000" />
<file name="musica.htm" server="ftp.corimaencolombia.com//www/" local="128777225775468750" remote="128781654600000000" />
</dwsync>